LICENSE
MANIFEST.in
README.rst
setup.py
django_simple_mixins.egg-info/PKG-INFO
django_simple_mixins.egg-info/SOURCES.txt
django_simple_mixins.egg-info/dependency_links.txt
django_simple_mixins.egg-info/top_level.txt
simplemixins/__init__.py
simplemixins/mixins.py