Metadata-Version: 1.1
Name: django-simple-mixins
Version: 0.1.0
Summary: Mixins to use for Djangos Class Based Views.
Home-page: https://github.com/drager/django-simple-mixins
Author: drager
Author-email: drager@programmers.se
License: BSD License
Platform: UNKNOWN
Classifier: Environment :: Web Environment
Classifier: Framework :: Django
Classifier: Intended Audience :: Developers
Classifier: License :: OSI Approved :: BSD License
Classifier: Programming Language :: Python
Classifier: Programming Language :: Python :: 2.6
Classifier: Programming Language :: Python :: 2.7
Classifier: Topic :: Internet :: WWW/HTTP
Classifier: Topic :: Internet :: WWW/HTTP :: Dynamic Content
